freecaptcha/__init__.py
freecaptcha/api_server.py
freecaptcha/image_generator.py
freecaptcha/noise_adder.py
py_free_captcha-0.2.1.dist-info/licenses/LICENSE
py_free_captcha-0.2.1.dist-info/METADATA
py_free_captcha-0.2.1.dist-info/WHEEL
py_free_captcha-0.2.1.dist-info/top_level.txt
py_free_captcha-0.2.1.dist-info/RECORD
