Metadata-Version: 2.4
Name: py-free-captcha
Version: 0.2.1
Summary: A zero JavaScript Captcha solution.
Author-email: Centrifudge <wladiwarszaw@gmail.com>
License: MIT
License-File: LICENSE
Requires-Dist: fastapi
Requires-Dist: uvicorn
Requires-Dist: pillow
Requires-Dist: numpy
Requires-Dist: pyvista
Dynamic: license-file
